micropython_uncrustify-1.0.0.post1.data/data/bin/uncrustify
micropython_uncrustify-1.0.0.post1.data/data/share/man/man1/uncrustify.1
micropython_uncrustify-1.0.0.post1.data/data/share/doc/uncrustify/ChangeLog
micropython_uncrustify-1.0.0.post1.data/data/share/doc/uncrustify/AUTHORS
micropython_uncrustify-1.0.0.post1.data/data/share/doc/uncrustify/BUGS
micropython_uncrustify-1.0.0.post1.data/data/share/doc/uncrustify/README.md
micropython_uncrustify-1.0.0.post1.data/data/share/doc/uncrustify/COPYING
micropython_uncrustify-1.0.0.post1.data/data/share/doc/uncrustify/HELP
micropython_uncrustify-1.0.0.post1.data/data/share/doc/uncrustify/examples/msvc.cfg
micropython_uncrustify-1.0.0.post1.data/data/share/doc/uncrustify/examples/ben2.cfg
micropython_uncrustify-1.0.0.post1.data/data/share/doc/uncrustify/examples/xsupplicant.cfg
micropython_uncrustify-1.0.0.post1.data/data/share/doc/uncrustify/examples/linux-indent.cfg
micropython_uncrustify-1.0.0.post1.data/data/share/doc/uncrustify/examples/MS-calling_conventions.cfg
micropython_uncrustify-1.0.0.post1.data/data/share/doc/uncrustify/examples/objc.cfg
micropython_uncrustify-1.0.0.post1.data/data/share/doc/uncrustify/examples/freebsd.cfg
micropython_uncrustify-1.0.0.post1.data/data/share/doc/uncrustify/examples/kr-indent.cfg
micropython_uncrustify-1.0.0.post1.data/data/share/doc/uncrustify/examples/linux.cfg
micropython_uncrustify-1.0.0.post1.data/data/share/doc/uncrustify/examples/klaus.cfg
micropython_uncrustify-1.0.0.post1.data/data/share/doc/uncrustify/examples/ben.cfg
micropython_uncrustify-1.0.0.post1.data/data/share/doc/uncrustify/examples/mono.cfg
micropython_uncrustify-1.0.0.post1.data/data/share/doc/uncrustify/examples/gnu-indent.cfg
micropython_uncrustify-1.0.0.post1.data/data/share/doc/uncrustify/examples/defaults.cfg
micropython_uncrustify-1.0.0.post1.data/data/share/doc/uncrustify/examples/sun.cfg
micropython_uncrustify-1.0.0.post1.data/data/share/doc/uncrustify/examples/d.cfg
micropython_uncrustify-1.0.0.post1.dist-info/AUTHORS
micropython_uncrustify-1.0.0.post1.dist-info/WHEEL
micropython_uncrustify-1.0.0.post1.dist-info/COPYING
micropython_uncrustify-1.0.0.post1.dist-info/top_level.txt
micropython_uncrustify-1.0.0.post1.dist-info/METADATA
micropython_uncrustify-1.0.0.post1.dist-info/RECORD
