Metadata-Version: 2.1
Name: micropython-uncrustify
Version: 1.0.0.post1
Project-URL: Homepage, https://github.com/dlech/micropython-uncrustify
License-File: COPYING
License-File: AUTHORS
